starwarden/__init__.py
starwarden/config.py
starwarden/github_api.py
starwarden/linkwarden_api.py
starwarden/main.py
starwarden/tui.py
starwarden/utils/__init__.py
starwarden/utils/logger.py
starwarden/utils/notify.py
starwarden-2.0.0.dist-info/WHEEL
starwarden-2.0.0.dist-info/METADATA
starwarden-2.0.0.dist-info/RECORD
