Metadata-Version: 2.3
Name: starwarden
Version: 2.0.0
Summary: Sync GitHub Stars to Linkwarden
Requires-Dist: apprise==1.9.6
Requires-Dist: pygithub==2.8.1
Requires-Dist: python-dotenv==1.1.1
Requires-Dist: requests==2.32.4
Requires-Dist: rich==14.2.0
Requires-Dist: tqdm==4.67.1
Requires-Python: >=3.13
